{
  "SET": {
    "name": "Ixalan",
    "code": "XLN",
    "magicCardsInfoCode": "xln",
    "releaseDate": "2017-09-29",
    "border": "black",
    "type": "expansion",
    "block": "Ixalan",
    "booster": [
      ["rare", "mythic rare"], "uncommon", "uncommon", "uncommon", "common", "common", "common", "common", "common", "common", "common", "common", "common", "common", "land", "marketing"
    ],
    "translations": {
      "de": "Ixalan",
      "fr": "Ixalan",
      "it": "Ixalan",
      "es": "Ixalan",
      "pt": "Ixalan",
      "ru": "Ixalan"
    },
    "mkm_name": "Ixalan",
    "mkm_id": 114
  },
  "SET_CORRECTIONS": [
  ]
}
